civic_interconnect/__init__.py
civic_interconnect/_version.py
civic_interconnect/cee/types.py
civic_interconnect/cee/procurement/__init__.py
civic_interconnect/cee/procurement/sme_explanations.py
civic_interconnect/cee/sme/sme_explanations.py
civic_interconnect/cep/__init__.py
civic_interconnect/cep/_version.py
civic_interconnect/cep/localization.py
civic_interconnect/cep/py.typed
civic_interconnect/cep/adapters/README.md
civic_interconnect/cep/adapters/__init__.py
civic_interconnect/cep/adapters/base.py
civic_interconnect/cep/adapters/demo_entities.py
civic_interconnect/cep/adapters/state_portal_example.py
civic_interconnect/cep/adapters/us_ca_municipality.py
civic_interconnect/cep/adapters/us_fec_campaign_finance.py
civic_interconnect/cep/adapters/us_il_vendor.py
civic_interconnect/cep/adapters/us_mn_municipality.py
civic_interconnect/cep/adapters/us_ny_municipality.py
civic_interconnect/cep/adapters/us_school_district.py
civic_interconnect/cep/adapters/procurement/sme/__init__.py
civic_interconnect/cep/adapters/procurement/sme/adapter.py
civic_interconnect/cep/adapters/procurement/sme/config.py
civic_interconnect/cep/adapters/procurement/sme/manifest.py
civic_interconnect/cep/adapters/procurement/us_il_vendor/__init__.py
civic_interconnect/cep/adapters/procurement/us_il_vendor/adapter.py
civic_interconnect/cep/adapters/procurement/us_il_vendor/config.py
civic_interconnect/cep/adapters/procurement/us_il_vendor/manifest.py
civic_interconnect/cep/codegen/README.md
civic_interconnect/cep/codegen/__init__.py
civic_interconnect/cep/codegen/python_constants.py
civic_interconnect/cep/codegen/rust_generated.py
civic_interconnect/cep/constants/entity_fields.py
civic_interconnect/cep/core/__init__.py
civic_interconnect/cep/core/attestation.py
civic_interconnect/cep/core/canonical.py
civic_interconnect/cep/core/error.py
civic_interconnect/cep/core/hash.py
civic_interconnect/cep/core/schema_registry.py
civic_interconnect/cep/core/timestamp.py
civic_interconnect-0.0.6.dist-info/licenses/LICENSE
civic_interconnect-0.0.6.dist-info/licenses/NOTICE
civic_interconnect-0.0.6.dist-info/METADATA
civic_interconnect-0.0.6.dist-info/WHEEL
civic_interconnect-0.0.6.dist-info/entry_points.txt
civic_interconnect-0.0.6.dist-info/top_level.txt
civic_interconnect-0.0.6.dist-info/RECORD
