Metadata-Version: 2.4
Name: civic-interconnect
Version: 0.0.6
Summary: Civic Interconnect: Civic Exchange Protocol schemas, validators, and tools for Python workflows
Author-email: Civic Interconnect <info@civic-interconnect.org>
License-Expression: Apache-2.0
Project-URL: Documentation, https://civic-interconnect.github.io/civic-interconnect/
Project-URL: Homepage, https://github.com/civic-interconnect/civic-interconnect
Project-URL: Issues, https://github.com/civic-interconnect/civic-interconnect/issues
Project-URL: Source, https://github.com/civic-interconnect/civic-interconnect
Keywords: civic,interconnect,civic-exchange-protocol,cep,government,open-data,provenance,jsonschema,pydantic
Classifier: Development Status :: 4 - Beta
Classifier: Intended Audience :: Developers
Classifier: Intended Audience :: Science/Research
Classifier: Intended Audience :: Education
Classifier: Natural Language :: English
Classifier: Operating System :: OS Independent
Classifier: Programming Language :: Python :: 3
Classifier: Programming Language :: Python :: 3 :: Only
Classifier: Programming Language :: Python :: 3.12
Classifier: Programming Language :: Python :: 3.13
Classifier: Topic :: Software Development :: Libraries :: Python Modules
Classifier: Topic :: Scientific/Engineering :: Information Analysis
Classifier: Typing :: Typed
Requires-Python: >=3.12
License-File: LICENSE
License-File: NOTICE
Requires-Dist: civic-data-identity-us-il
Requires-Dist: jsonschema
Requires-Dist: pandas
Requires-Dist: PyYAML
Requires-Dist: referencing
Requires-Dist: typer
Provides-Extra: dev
Requires-Dist: build; extra == "dev"
Requires-Dist: defusedxml; extra == "dev"
Requires-Dist: maturin; extra == "dev"
Requires-Dist: pre-commit; extra == "dev"
Requires-Dist: pyright; extra == "dev"
Requires-Dist: pytest; extra == "dev"
Requires-Dist: pytest-asyncio; extra == "dev"
Requires-Dist: pytest-cov; extra == "dev"
Requires-Dist: pytest-env; extra == "dev"
Requires-Dist: twine; extra == "dev"
Requires-Dist: validate-pyproject; extra == "dev"
Provides-Extra: docs
Requires-Dist: mike; extra == "docs"
Requires-Dist: mkdocs; extra == "docs"
Requires-Dist: mkdocs-gen-files; extra == "docs"
Requires-Dist: mkdocs-git-revision-date-localized-plugin; extra == "docs"
Requires-Dist: mkdocs-include-markdown-plugin; extra == "docs"
Requires-Dist: mkdocs-literate-nav; extra == "docs"
Requires-Dist: mkdocs-material; extra == "docs"
Requires-Dist: mkdocs-static-i18n; extra == "docs"
Requires-Dist: mkdocstrings[python]>=0.18; extra == "docs"
Requires-Dist: ruff; extra == "docs"
Dynamic: license-file
